edb_deployment-3.5.1.data/scripts/edb-deployment
edbdeploy/__init__.py
edbdeploy/action.py
edbdeploy/ansible.py
edbdeploy/cli.py
edbdeploy/cloud.py
edbdeploy/command.py
edbdeploy/errors.py
edbdeploy/installation.py
edbdeploy/options.py
edbdeploy/password.py
edbdeploy/project.py
edbdeploy/specifications.py
edbdeploy/system.py
edbdeploy/terraform.py
edbdeploy/tpaexec.py
edbdeploy/virtualbox.py
edbdeploy/vmware.py
edbdeploy/commands/__init__.py
edbdeploy/commands/aurora.py
edbdeploy/commands/aws.py
edbdeploy/commands/aws_pot.py
edbdeploy/commands/azure.py
edbdeploy/commands/azure_db.py
edbdeploy/commands/azure_pot.py
edbdeploy/commands/baremetal.py
edbdeploy/commands/default.py
edbdeploy/commands/gcloud.py
edbdeploy/commands/gcloud_pot.py
edbdeploy/commands/gcloud_sql.py
edbdeploy/commands/rds.py
edbdeploy/commands/virtualbox.py
edbdeploy/commands/vmware.py
edbdeploy/data/ansible/DBT-2.yml
edbdeploy/data/ansible/EDB-Always-On.yml
edbdeploy/data/ansible/EDB-RA-1.yml
edbdeploy/data/ansible/EDB-RA-2.yml
edbdeploy/data/ansible/EDB-RA-3.yml
edbdeploy/data/ansible/EDB-RA.yml
edbdeploy/data/ansible/HammerDB-DBaaS.yml
edbdeploy/data/ansible/HammerDB-TPROC-C.yml
edbdeploy/data/ansible/roles/bdr_pot_setup/defaults/main.yml
edbdeploy/data/ansible/roles/bdr_pot_setup/handlers/main.yml
edbdeploy/data/ansible/roles/bdr_pot_setup/tasks/bdr_setup.yml
edbdeploy/data/ansible/roles/bdr_pot_setup/tasks/main.yml
edbdeploy/data/ansible/roles/bdr_pot_setup/tasks/os_configure_user.yml
edbdeploy/data/ansible/roles/bdr_pot_setup/tasks/pem_server_certs.yml
edbdeploy/data/ansible/roles/bdr_pot_setup/tasks/pem_server_probe_alert.yml
edbdeploy/data/ansible/roles/bdr_pot_setup/tasks/pg_create_user.yml
edbdeploy/data/ansible/roles/bdr_pot_setup/tasks/pg_hba_rule.yml
edbdeploy/data/ansible/roles/bdr_pot_setup/tasks/pg_pot_hba.yml
edbdeploy/data/ansible/roles/bdr_pot_setup/tasks/pg_pot_scripts.yml
edbdeploy/data/ansible/roles/bdr_pot_setup/tasks/pg_user_pgpass.yml
edb_deployment-3.5.1.dist-info/LICENSE.md
edb_deployment-3.5.1.dist-info/METADATA
edb_deployment-3.5.1.dist-info/WHEEL
edb_deployment-3.5.1.dist-info/top_level.txt
edb_deployment-3.5.1.dist-info/RECORD
